spotdlQt/app.py
spotdlQt-1.0.4.dist-info/LICENSE
spotdlQt-1.0.4.dist-info/METADATA
spotdlQt-1.0.4.dist-info/WHEEL
spotdlQt-1.0.4.dist-info/entry_points.txt
spotdlQt-1.0.4.dist-info/top_level.txt
spotdlQt-1.0.4.dist-info/RECORD
