Metadata-Version: 2.1
Name: spotdlQt
Version: 1.0.4
Summary: A small gui for spotdl using qt written in python
Author-email: Magi3r <magier.mit.f3erball@gmail.com>
Project-URL: Repository, https://github.com/Magi3r/spotdlQt
Project-URL: Issues, https://github.com/Magi3r/spotdlQt/issues
Keywords: spotdl,qt6,downloader,music
Classifier: Programming Language :: Python :: 3
Classifier: License :: OSI Approved :: Apache Software License
Classifier: Operating System :: OS Independent
Requires-Python: >=3.8
License-File: LICENSE
Requires-Dist: pyqt6 ==6.7.0
Requires-Dist: spotdl ==4.2.5
